scripts/json_rpc_client.py
scripts/modbus_tcp_slave.py
scripts/tolk_server.py
scripts/__init__.py
tolk/json_rpc.py
tolk/exceptions.py
tolk/__init__.py
tolk/handler.py
Tolk-0.2.1.dist-info/top_level.txt
Tolk-0.2.1.dist-info/WHEEL
Tolk-0.2.1.dist-info/RECORD
Tolk-0.2.1.dist-info/metadata.json
Tolk-0.2.1.dist-info/entry_points.txt
Tolk-0.2.1.dist-info/METADATA
Tolk-0.2.1.dist-info/DESCRIPTION.rst
