Metadata-Version: 2.0
Name: Tolk
Version: 0.2.1
Summary: JSON-RPC proxy for talking Modbus over RTU and TCP.
Home-page: https://github.com/AdvancedClimateSystems/Tolk/
Author: Auke Willem Oosterhoff
Author-email: oosterhoff@baopt.nl
License: MPL
Platform: UNKNOWN
Classifier: Development Status :: 3 - Alpha
Classifier: Intended Audience :: Developers
Classifier: License :: OSI Approved :: Mozilla Public License 2.0 (MPL 2.0)
Classifier: Operating System :: Unix
Classifier: Programming Language :: Python :: 2.6
Classifier: Programming Language :: Python :: 2.7
Classifier: Topic :: Software Development :: Embedded Systems
Requires-Dist: docopt (>=0.6.2)
Requires-Dist: logbook (>=0.11.2)
Requires-Dist: modbus-tk (>=0.4.3)
Requires-Dist: python-jsonrpc (>=0.7.12)
